manylabels/__init__.py
manylabels/_manylabels.py
manylabels/py.typed
manylabels-0.1.0.dist-info/LICENSE
manylabels-0.1.0.dist-info/METADATA
manylabels-0.1.0.dist-info/WHEEL
manylabels-0.1.0.dist-info/top_level.txt
manylabels-0.1.0.dist-info/RECORD
