Metadata-Version: 2.1
Name: manylabels
Version: 0.1.0
Summary: Automatically add multiple x-axis labels to your matplotlib subplots.
Home-page: https://github.com/mshumko/manylabels
Author: Mykhaylo Shumko
Author-email: "Mykhaylo Shumko" <msshumko@gmail.com>
License: GNU General Public License v3 (GPLv3)
Classifier: License :: OSI Approved :: GNU General Public License v3 (GPLv3)
Requires-Python: >=3.9
License-File: LICENSE
